loupiotes/__init__.py
loupiotes/intensity.py
loupiotes/solar_coordinates.py
loupiotes/spots/__init__.py
loupiotes/spots/collection.py
loupiotes/spots/generator.py
loupiotes/spots/multi_channel.py
loupiotes/spots/spotmodel.py
loupiotes/tables/__init__.py
loupiotes/tables/sing_2010_kepler.fit
loupiotes/tables/tables.py
loupiotes-1.0.dist-info/LICENSE
loupiotes-1.0.dist-info/METADATA
loupiotes-1.0.dist-info/WHEEL
loupiotes-1.0.dist-info/top_level.txt
loupiotes-1.0.dist-info/RECORD
