Metadata-Version: 2.1
Name: loupiotes
Version: 1.0
Summary: Module for starspot modelling
Author-email: "Sylvain N. Breton" <sylvain.breton@inaf.it>
License: 
Project-URL: Homepage, https://gitlab.com/sybreton/loupiotes
Keywords: stellar physics,photometry,starspot modelling
Classifier: Programming Language :: Python :: 3
Classifier: License :: OSI Approved :: CEA CNRS Inria Logiciel Libre License, version 2.1 (CeCILL-2.1)
Classifier: Operating System :: OS Independent
Requires-Python: >=3.7
License-File: LICENSE
Requires-Dist: numpy
Requires-Dist: pandas
Requires-Dist: matplotlib
Requires-Dist: astropy
Requires-Dist: scipy
Requires-Dist: numba
Requires-Dist: tqdm
Requires-Dist: pymc
Requires-Dist: arviz
Requires-Dist: pytensor
Requires-Dist: pathos
